{"onboarding":{"$contentActions":[{"input":{"bypass":false,"$cardContent":{"document":{"id":"e3e1d527-7160-4d2e-8357-064a6acaa334","type":"text/plain","content":"Entrada do usuário"},"editable":false,"deletable":false,"position":"right","editing":false},"$invalid":false},"$invalid":false}],"$conditionOutputs":[{"stateId":"welcome","$connId":"con_3","$id":"b8932815-c227-47b0-ad83-bd0e0002585f","conditions":[{"source":"input","comparison":"exists","values":[]}],"$invalid":false}],"$enteringCustomActions":[],"$leavingCustomActions":[],"$inputSuggestions":[],"$defaultOutput":{"stateId":"welcome","$invalid":false},"$tags":[],"id":"onboarding","root":true,"$title":"Início","$position":{"top":"17px","left":"619px"},"$invalidContentActions":false,"$invalidOutputs":false,"$invalidCustomActions":false,"$invalid":false},"fallback":{"$contentActions":[{"input":{"bypass":true,"$cardContent":{"document":{"id":"2c9301bc-c674-4ec0-b742-3cb4a03f7dcc","type":"text/plain","content":"Entrada do usuário"},"editable":false,"deletable":true,"position":"right","editing":false},"$invalid":false},"$invalid":false}],"$conditionOutputs":[{"stateId":"error","conditions":[{"source":"input","comparison":"matches","values":[".*"]}],"$id":"80db4cbb-f3be-4169-9b1e-bfae01807380","$connId":"con_8","$invalid":false}],"$enteringCustomActions":[],"$leavingCustomActions":[],"$inputSuggestions":[],"$defaultOutput":{"stateId":"onboarding","$invalid":false},"$tags":[],"id":"fallback","$title":"Exceções","$position":{"top":"0px","left":"1060.06px"},"$invalidContentActions":false,"$invalidOutputs":false,"$invalidCustomActions":false,"$invalid":false},"welcome":{"$contentActions":[{"action":{"$id":"c85bfc78-3128-40ab-b5ed-6fe2e2c0a84a","type":"SendMessage","settings":{"id":"00000000-0000-0000-0000-000000000001","type":"text/plain","content":"Olá, espero que esteja bem.\nSou a Lora, responsável por\n passar os valores da Take.","metadata":{}},"$cardContent":{"document":{"id":"00000000-0000-0000-0000-000000000001","type":"text/plain","content":"Olá, espero que esteja bem.\nSou a Lora, responsável por\n passar os valores da Take."},"editable":true,"deletable":true,"position":"left","editing":false}},"$invalid":false},{"action":{"$id":"2a9758b1-3a73-4b8b-8313-5ca2f3d36d8d","type":"SendMessage","settings":{"id":"91906313-f541-4a83-8f6d-f05ff6065c0f","type":"application/vnd.lime.chatstate+json","content":{"state":"composing","interval":1000}},"$cardContent":{"document":{"id":"91906313-f541-4a83-8f6d-f05ff6065c0f","type":"application/vnd.lime.chatstate+json","content":{"state":"composing","interval":1000}},"editable":true,"deletable":true,"position":"left"}},"$invalid":false},{"action":{"$id":"5f6c08c0-9229-4064-b012-93a1d491556c","type":"SendMessage","settings":{"id":"988c8110-833d-428d-934e-269093c4f8ac","type":"text/plain","content":"Mesmo sendo um robô, sem consciência sobre o que são valores, ainda posso te ajudar de alguma forma.","metadata":{}},"$cardContent":{"document":{"id":"988c8110-833d-428d-934e-269093c4f8ac","type":"text/plain","content":"Mesmo sendo um robô, sem consciência sobre o que são valores, ainda posso te ajudar de alguma forma."},"editable":true,"deletable":true,"position":"left"}},"$invalid":false},{"action":{"$id":"445b8902-5056-43a7-88ed-a58a842d1704","type":"SendMessage","settings":{"id":"37f6b688-9440-4576-b765-13f81f105227","type":"application/vnd.lime.chatstate+json","content":{"state":"composing","interval":1000}},"$cardContent":{"document":{"id":"37f6b688-9440-4576-b765-13f81f105227","type":"application/vnd.lime.chatstate+json","content":{"state":"composing","interval":1000}},"editable":true,"deletable":true,"position":"left"}},"$invalid":false},{"action":{"$id":"38dd3f0f-4e7f-4c3e-934b-498583460124","type":"SendMessage","settings":{"id":"67d5b228-f624-481c-8d49-cecc25e25a20","type":"text/plain","content":"A cultura Take tem como \nbase 6 valores que são:","metadata":{}},"$cardContent":{"document":{"id":"67d5b228-f624-481c-8d49-cecc25e25a20","type":"text/plain","content":"A cultura Take tem como \nbase 6 valores que são:"},"editable":true,"deletable":true,"position":"left"}},"$invalid":false},{"input":{"bypass":true,"$cardContent":{"document":{"id":"e961d608-1fd0-4f83-9328-47a684af5207","type":"text/plain","content":"Entrada do usuário"},"editable":false,"deletable":true,"position":"right","editing":false},"$invalid":false},"$invalid":false}],"$conditionOutputs":[{"stateId":"116c1a7d-f5fa-482d-b698-a442fba24110","$connId":"con_13","$id":"33ac90fa-3510-49bf-bae0-7295428a548d","conditions":[{"source":"input","comparison":"exists","values":[]}],"$invalid":false}],"$enteringCustomActions":[],"$leavingCustomActions":[],"$inputSuggestions":[],"$defaultOutput":{"stateId":"116c1a7d-f5fa-482d-b698-a442fba24110","$invalid":false},"$tags":[],"id":"welcome","$title":"Boas vindas","$position":{"top":"182px","left":"619px"},"$invalidContentActions":false,"$invalidOutputs":false,"$invalidCustomActions":false,"$invalid":false},"error":{"$contentActions":[{"action":{"$id":"922c0524-9286-4358-aa9a-bd19bf874cfb","type":"SendMessage","settings":{"id":"00000000-0000-0000-0000-000000000002","type":"application/vnd.lime.chatstate+json","content":{"state":"composing","interval":1000}},"$cardContent":{"document":{"id":"00000000-0000-0000-0000-000000000002","type":"application/vnd.lime.chatstate+json","content":{"state":"composing","interval":1000}},"editable":true,"deletable":true,"position":"left","editing":false}},"$invalid":false},{"action":{"$id":"c88f3d58-4cdb-4987-b3fd-ee2a165b8a4a","type":"SendMessage","settings":{"id":"00000000-0000-0000-0000-000000000003","type":"text/plain","content":"Desculpe, não consegui entender!"},"$cardContent":{"document":{"id":"00000000-0000-0000-0000-000000000003","type":"text/plain","content":"Desculpe, não consegui entender!"},"editable":true,"deletable":true,"position":"left","editing":false}},"$invalid":false},{"input":{"bypass":true,"$cardContent":{"document":{"id":"26eb975a-829f-44aa-8557-39d218a8b03b","type":"text/plain","content":"Entrada do usuário"},"editable":false,"deletable":true,"position":"right","editing":false},"$invalid":false},"$invalid":false}],"$conditionOutputs":[],"$enteringCustomActions":[],"$leavingCustomActions":[],"$inputSuggestions":[],"$defaultOutput":{"stateId":"onboarding","$invalid":false},"$tags":[],"id":"error","$title":"Erro padrão","$position":{"top":"0px","left":"1276.19px"},"$invalidContentActions":false,"$invalidOutputs":false,"$invalidCustomActions":false,"$invalid":false},"116c1a7d-f5fa-482d-b698-a442fba24110":{"$contentActions":[{"action":{"$id":"0bc1f3c0-bf60-452f-9347-555feaf927f3","type":"SendMessage","settings":{"id":"2977b4d0-c179-466a-b33f-7022e28273c5","type":"application/vnd.lime.chatstate+json","content":{"state":"composing","interval":1000},"metadata":{}},"$cardContent":{"document":{"id":"2977b4d0-c179-466a-b33f-7022e28273c5","type":"application/vnd.lime.chatstate+json","content":{"state":"composing","interval":1000}},"editable":true,"deletable":true,"position":"left"}},"$invalid":false},{"action":{"$id":"571f254c-5dde-4264-8004-a2860edeade2","type":"SendMessage","settings":{"id":"87904ef3-6fc2-446f-bdfb-a28cbf742c5c","type":"application/vnd.lime.collection+json","content":{"itemType":"application/vnd.lime.document-select+json","items":[{"header":{"type":"application/vnd.lime.media-link+json","value":{"title":"Take.Be","text":"Pessoas em 1º lugar.","type":"image/png","uri":"https://i.imgur.com/egcqSXL.png","aspectRatio":"2:1"}},"options":[{"label":{"type":"text/plain","value":"💙 Saber mais"},"value":null}],"id":0,"editing":false},{"header":{"type":"application/vnd.lime.media-link+json","value":{"title":"Take.Team","text":"Em nosso time, cada pessoa dá o seu melhor.","type":"image/png","uri":"https://i.imgur.com/3ClrrX8.png","aspectRatio":"2:1"}},"options":[{"label":{"type":"text/plain","value":"🏳️ Saber mais"},"value":null}],"id":1,"editing":false},{"header":{"type":"application/vnd.lime.media-link+json","value":{"title":"Take.Excellence","text":"Excelente é o nosso ponto de partida","type":"image/png","uri":"https://i.imgur.com/6u29CMb.png","aspectRatio":"2:1"}},"options":[{"label":{"type":"text/plain","value":"⭐ Saber mais"},"value":null}],"editing":false,"id":2},{"header":{"type":"application/vnd.lime.media-link+json","value":{"title":"Take.Charge","text":"Apropriar-se para fazer a diferença","type":"image/png","uri":"https://i.imgur.com/SC7w5vT.png","aspectRatio":"2:1"}},"options":[{"label":{"type":"text/plain","value":"⚡ Saber mais"},"value":null}],"editing":false,"id":3},{"header":{"type":"application/vnd.lime.media-link+json","value":{"title":"Take.Simple","text":"Simplicidade é o último grau de sofisticação.","type":"image/png","uri":"https://i.imgur.com/FMd6GvD.png","aspectRatio":"2:1"}},"options":[{"label":{"type":"text/plain","value":"🎯 Saber mais"},"value":null}],"editing":false,"id":4},{"header":{"type":"application/vnd.lime.media-link+json","value":{"title":"Take.Higher","text":"Pensar grande e ir além.","type":"image/png","uri":"https://i.imgur.com/6vSwqk1.png","aspectRatio":"2:1"}},"options":[{"label":{"type":"text/plain","value":"🚀 Saber mais"},"value":null}],"editing":false,"id":5},{"header":{"type":"application/vnd.lime.media-link+json","value":{"title":"Desafio","text":"......","type":"image/png","uri":"https://i.imgur.com/iJPXxdo.png","aspectRatio":"2:1"}},"options":[{"label":{"type":"text/plain","value":"Fazer desafio"},"value":null}],"editing":false,"id":6}]},"metadata":{}},"$cardContent":{"document":{"id":"87904ef3-6fc2-446f-bdfb-a28cbf742c5c","type":"application/vnd.lime.collection+json","content":{"itemType":"application/vnd.lime.document-select+json","items":[{"header":{"type":"application/vnd.lime.media-link+json","value":{"title":"Take.Be","text":"Pessoas em 1º lugar.","type":"image/png","uri":"https://i.imgur.com/egcqSXL.png","aspectRatio":"2:1"}},"options":[{"label":{"type":"text/plain","value":"💙 Saber mais"},"value":null}],"id":0,"editing":false},{"header":{"type":"application/vnd.lime.media-link+json","value":{"title":"Take.Team","text":"Em nosso time, cada pessoa dá o seu melhor.","type":"image/png","uri":"https://i.imgur.com/3ClrrX8.png","aspectRatio":"2:1"}},"options":[{"label":{"type":"text/plain","value":"🏳️ Saber mais"},"value":null}],"id":1,"editing":false},{"header":{"type":"application/vnd.lime.media-link+json","value":{"title":"Take.Excellence","text":"Excelente é o nosso ponto de partida","type":"image/png","uri":"https://i.imgur.com/6u29CMb.png","aspectRatio":"2:1"}},"options":[{"label":{"type":"text/plain","value":"⭐ Saber mais"},"value":null}],"editing":false,"id":2},{"header":{"type":"application/vnd.lime.media-link+json","value":{"title":"Take.Charge","text":"Apropriar-se para fazer a diferença","type":"image/png","uri":"https://i.imgur.com/SC7w5vT.png","aspectRatio":"2:1"}},"options":[{"label":{"type":"text/plain","value":"⚡ Saber mais"},"value":null}],"editing":false,"id":3},{"header":{"type":"application/vnd.lime.media-link+json","value":{"title":"Take.Simple","text":"Simplicidade é o último grau de sofisticação.","type":"image/png","uri":"https://i.imgur.com/FMd6GvD.png","aspectRatio":"2:1"}},"options":[{"label":{"type":"text/plain","value":"🎯 Saber mais"},"value":null}],"editing":false,"id":4},{"header":{"type":"application/vnd.lime.media-link+json","value":{"title":"Take.Higher","text":"Pensar grande e ir além.","type":"image/png","uri":"https://i.imgur.com/6vSwqk1.png","aspectRatio":"2:1"}},"options":[{"label":{"type":"text/plain","value":"🚀 Saber mais"},"value":null}],"editing":false,"id":5},{"header":{"type":"application/vnd.lime.media-link+json","value":{"title":"Desafio","text":"......","type":"image/png","uri":"https://i.imgur.com/iJPXxdo.png","aspectRatio":"2:1"}},"options":[{"label":{"type":"text/plain","value":"Fazer desafio"},"value":null}],"editing":false,"id":6}]}},"editable":true,"deletable":true,"position":"left"}},"$invalid":false},{"input":{"bypass":false,"$cardContent":{"document":{"id":"ef4c3e3b-48d2-4b08-b222-3eb071d79e76","type":"text/plain","textContent":"Entrada do usuário","content":"Entrada do usuário"},"editable":false,"deletable":true,"position":"right","editing":false},"$invalid":false},"$invalid":false}],"$conditionOutputs":[{"stateId":"5fb727dd-d01a-4837-9e12-e2f651e8a394","$connId":"con_18","$id":"cc41babe-9f3b-4023-a559-c3d7e5d604da","conditions":[{"source":"input","comparison":"exists","values":[]}],"$invalid":false}],"$enteringCustomActions":[],"$leavingCustomActions":[{"$id":"07df08a8-9817-4dbb-bc4d-d37925a0536d","type":"SetVariable","$title":"Definir variável","$invalid":false,"settings":{"variable":"nomeValor","value":"{{input.content}}"},"conditions":[]}],"$inputSuggestions":["💙 Saber mais","🏳️ Saber mais","⭐ Saber mais","⚡ Saber mais","🎯 Saber mais","🚀 Saber mais","Fazer desafio"],"$defaultOutput":{"stateId":"fallback","$invalid":false},"$tags":[],"id":"116c1a7d-f5fa-482d-b698-a442fba24110","root":false,"$title":"Carousel Valores","$position":{"top":"303px","left":"619px"},"$invalidContentActions":false,"$invalidOutputs":false,"$invalidCustomActions":false,"$invalid":false},"9787c43b-eba7-4134-b201-9e610aafae51":{"$contentActions":[{"action":{"$id":"10c8a822-1de5-4898-8cca-336d698acd7e","type":"SendMessage","settings":{"id":"75257a8d-e359-434a-a335-b9af714d4f67","type":"application/vnd.lime.chatstate+json","content":{"state":"composing","interval":1000}},"$cardContent":{"document":{"id":"75257a8d-e359-434a-a335-b9af714d4f67","type":"application/vnd.lime.chatstate+json","content":{"state":"composing","interval":1000}},"editable":true,"deletable":true,"position":"left"}},"$invalid":false},{"action":{"$id":"d46780e8-9c50-4006-ae29-22a95942256a","type":"SendMessage","settings":{"id":"f5fb465b-9cb4-4dff-aeeb-5cf357bae95e","type":"text/plain","content":"A Take é feita por pessoas e para pessoas. Nossas relações são transparentes e humanizadas.\n","metadata":{}},"$cardContent":{"document":{"id":"f5fb465b-9cb4-4dff-aeeb-5cf357bae95e","type":"text/plain","content":"A Take é feita por pessoas e para pessoas. Nossas relações são transparentes e humanizadas.\n"},"editable":true,"deletable":true,"position":"left"}},"$invalid":false},{"action":{"$id":"1cec209b-79ff-47f3-b4f8-7c0f8f67b261","type":"SendMessage","settings":{"id":"6badf415-e047-4e1c-b154-21fb390e665d","type":"application/vnd.lime.chatstate+json","content":{"state":"composing","interval":1000}},"$cardContent":{"document":{"id":"6badf415-e047-4e1c-b154-21fb390e665d","type":"application/vnd.lime.chatstate+json","content":{"state":"composing","interval":1000}},"editable":true,"deletable":true,"position":"left"}},"$invalid":false},{"action":{"$id":"0729e2d8-b3ca-4a10-bcec-02fd6e80826d","type":"SendMessage","settings":{"id":"cb452cb6-ab2e-4bad-9f53-26f58dcf5b09","type":"text/plain","content":"Cada cliente, cada parceiro e cada Take.Ser é valorizado e respeitado em sua individualidade e está presente em cada bit de nossa empresa.\n","metadata":{}},"$cardContent":{"document":{"id":"cb452cb6-ab2e-4bad-9f53-26f58dcf5b09","type":"text/plain","content":"Cada cliente, cada parceiro e cada Take.Ser é valorizado e respeitado em sua individualidade e está presente em cada bit de nossa empresa.\n"},"editable":true,"deletable":true,"position":"left"}},"$invalid":false},{"input":{"bypass":true,"$cardContent":{"document":{"id":"b3a44037-ed19-49ef-b83e-9e98b5ee4628","type":"text/plain","textContent":"Entrada do usuário","content":"Entrada do usuário"},"editable":false,"deletable":true,"position":"right","editing":false},"$invalid":false},"$invalid":false}],"$conditionOutputs":[],"$enteringCustomActions":[],"$leavingCustomActions":[],"$inputSuggestions":[],"$defaultOutput":{"stateId":"03b0c9e3-a6ce-466f-9f66-e202c5a4010b","$invalid":false},"$tags":[],"id":"9787c43b-eba7-4134-b201-9e610aafae51","root":false,"$title":"Take.Be","$position":{"top":"396px","left":"333px"},"$invalidContentActions":false,"$invalidOutputs":false,"$invalidCustomActions":false,"$invalid":false},"be256784-da9a-41a4-8529-f23feb121f1a":{"$contentActions":[{"action":{"$id":"4b738251-414c-47ae-801b-531afa8066d0","type":"SendMessage","settings":{"id":"f85127ce-8870-4043-8a80-d4916f936cdd","type":"application/vnd.lime.chatstate+json","content":{"state":"composing","interval":1000}},"$cardContent":{"document":{"id":"f85127ce-8870-4043-8a80-d4916f936cdd","type":"application/vnd.lime.chatstate+json","content":{"state":"composing","interval":1000}},"editable":true,"deletable":true,"position":"left"}},"$invalid":false},{"action":{"$id":"0bdc9900-ba06-4c0f-942f-90f8208400c8","type":"SendMessage","settings":{"id":"415f09a8-ddb5-497d-84c6-e3f39949cba8","type":"text/plain","content":"Sabemos que o que faz uma equipe incrível são pessoas incríveis em cooperação. Assim, cada Take.ser busca cumprir sua parte para garantir a vitória do time.","metadata":{}},"$cardContent":{"document":{"id":"415f09a8-ddb5-497d-84c6-e3f39949cba8","type":"text/plain","content":"Sabemos que o que faz uma equipe incrível são pessoas incríveis em cooperação. Assim, cada Take.ser busca cumprir sua parte para garantir a vitória do time."},"editable":true,"deletable":true,"position":"left"}},"$invalid":false},{"input":{"bypass":true,"$cardContent":{"document":{"id":"243b1176-c388-4de2-9b90-7e3864ea4651","type":"text/plain","textContent":"Entrada do usuário","content":"Entrada do usuário"},"editable":false,"deletable":true,"position":"right","editing":false},"$invalid":false},"$invalid":false}],"$conditionOutputs":[],"$enteringCustomActions":[],"$leavingCustomActions":[],"$inputSuggestions":[],"$defaultOutput":{"stateId":"03b0c9e3-a6ce-466f-9f66-e202c5a4010b","$invalid":false},"$tags":[],"id":"be256784-da9a-41a4-8529-f23feb121f1a","root":false,"$title":"Take.Team","$position":{"top":"503px","left":"332px"},"$invalidContentActions":false,"$invalidOutputs":false,"$invalidCustomActions":false,"$invalid":false},"e585e39b-f0da-4a8f-8e97-523d7f4d961b":{"$contentActions":[{"action":{"$id":"569c563f-3a79-41b5-a67f-3098752b3b13","type":"SendMessage","settings":{"id":"b6ee74f4-60f7-4381-8b89-562817fb5187","type":"application/vnd.lime.chatstate+json","content":{"state":"composing","interval":1000}},"$cardContent":{"document":{"id":"b6ee74f4-60f7-4381-8b89-562817fb5187","type":"application/vnd.lime.chatstate+json","content":{"state":"composing","interval":1000}},"editable":true,"deletable":true,"position":"left"}},"$invalid":false},{"action":{"$id":"a78ca873-2d11-4e15-a001-dd428c17cf54","type":"SendMessage","settings":{"id":"10b6f168-0b1a-410f-a1b8-348fdff15ef0","type":"text/plain","content":"Com nosso espírito geek e nossa disposição para aprender e crescer, buscamos estar sempre um passo a frente e superarmos os mais exigentes padrões.","metadata":{}},"$cardContent":{"document":{"id":"10b6f168-0b1a-410f-a1b8-348fdff15ef0","type":"text/plain","content":"Com nosso espírito geek e nossa disposição para aprender e crescer, buscamos estar sempre um passo a frente e superarmos os mais exigentes padrões."},"editable":true,"deletable":true,"position":"left"}},"$invalid":false},{"input":{"bypass":true,"$cardContent":{"document":{"id":"acde9da2-fc05-439c-823e-021f1bac2fb9","type":"text/plain","textContent":"Entrada do usuário","content":"Entrada do usuário"},"editable":false,"deletable":true,"position":"right","editing":false},"$invalid":false},"$invalid":false}],"$conditionOutputs":[],"$enteringCustomActions":[],"$leavingCustomActions":[],"$inputSuggestions":[],"$defaultOutput":{"stateId":"03b0c9e3-a6ce-466f-9f66-e202c5a4010b","$invalid":false},"$tags":[],"id":"e585e39b-f0da-4a8f-8e97-523d7f4d961b","root":false,"$title":"Take.Excellence","$position":{"top":"615px","left":"336px"},"$invalidContentActions":false,"$invalidOutputs":false,"$invalidCustomActions":false,"$invalid":false},"07fb5a96-5234-4b4a-8abc-823fe45b6bd7":{"$contentActions":[{"action":{"$id":"9055e929-3957-4441-b2c8-b08948e39577","type":"SendMessage","settings":{"id":"878f5a6f-0a4d-4e8f-8818-a09fcd737df7","type":"application/vnd.lime.chatstate+json","content":{"state":"composing","interval":1000}},"$cardContent":{"document":{"id":"878f5a6f-0a4d-4e8f-8818-a09fcd737df7","type":"application/vnd.lime.chatstate+json","content":{"state":"composing","interval":1000}},"editable":true,"deletable":true,"position":"left"}},"$invalid":false},{"action":{"$id":"fee8da4f-6752-400d-8a63-83553b3d0129","type":"SendMessage","settings":{"id":"8e91dd9f-ee6c-48c0-986d-0f64e0b0ef0e","type":"text/plain","content":"Apostamos em profissionais que chamam a responsabilidade para si e que, sem medo de ousar, transformam o mundo a sua volta, com muita competência e criatividade!\n","metadata":{}},"$cardContent":{"document":{"id":"8e91dd9f-ee6c-48c0-986d-0f64e0b0ef0e","type":"text/plain","content":"Apostamos em profissionais que chamam a responsabilidade para si e que, sem medo de ousar, transformam o mundo a sua volta, com muita competência e criatividade!\n"},"editable":true,"deletable":true,"position":"left"}},"$invalid":false},{"input":{"bypass":true,"$cardContent":{"document":{"id":"67978db0-7f5e-4b6a-a3c5-967898253aaa","type":"text/plain","textContent":"Entrada do usuário","content":"Entrada do usuário"},"editable":false,"deletable":true,"position":"right","editing":false},"$invalid":false},"$invalid":false}],"$conditionOutputs":[],"$enteringCustomActions":[],"$leavingCustomActions":[],"$inputSuggestions":[],"$defaultOutput":{"stateId":"03b0c9e3-a6ce-466f-9f66-e202c5a4010b","$invalid":false},"$tags":[],"id":"07fb5a96-5234-4b4a-8abc-823fe45b6bd7","root":false,"$title":"Take.Charge","$position":{"top":"397px","left":"886px"},"$invalidContentActions":false,"$invalidOutputs":false,"$invalidCustomActions":false,"$invalid":false},"ec948a00-6f35-4597-b25d-3e610c4c8062":{"$contentActions":[{"action":{"$id":"7aa52fa1-8b19-474c-839e-c3f56efda085","type":"SendMessage","settings":{"id":"70ac361c-0517-415e-b45c-03792f94874f","type":"application/vnd.lime.chatstate+json","content":{"state":"composing","interval":1000}},"$cardContent":{"document":{"id":"70ac361c-0517-415e-b45c-03792f94874f","type":"application/vnd.lime.chatstate+json","content":{"state":"composing","interval":1000}},"editable":true,"deletable":true,"position":"left"}},"$invalid":false},{"action":{"$id":"47c431cf-e8b0-484d-8a7e-49f193c305ae","type":"SendMessage","settings":{"id":"ceb2e2d6-4337-404f-9d61-2d8165ee4a11","type":"text/plain","content":"Mantemos o foco no \nessencial. Menos é mais.","metadata":{}},"$cardContent":{"document":{"id":"ceb2e2d6-4337-404f-9d61-2d8165ee4a11","type":"text/plain","content":"Mantemos o foco no \nessencial. Menos é mais."},"editable":true,"deletable":true,"position":"left"}},"$invalid":false},{"input":{"bypass":true,"$cardContent":{"document":{"id":"6c78240e-8ff1-48b3-a108-762ec32eabb6","type":"text/plain","textContent":"Entrada do usuário","content":"Entrada do usuário"},"editable":false,"deletable":true,"position":"right","editing":false},"$invalid":false},"$invalid":false}],"$conditionOutputs":[],"$enteringCustomActions":[],"$leavingCustomActions":[],"$inputSuggestions":[],"$defaultOutput":{"stateId":"03b0c9e3-a6ce-466f-9f66-e202c5a4010b","$invalid":false},"$tags":[],"id":"ec948a00-6f35-4597-b25d-3e610c4c8062","root":false,"$title":"Take.Simple","$position":{"top":"615px","left":"887px"},"$invalidContentActions":false,"$invalidOutputs":false,"$invalidCustomActions":false,"$invalid":false},"9501bb11-db9a-4a85-b969-74e75cb0d2f4":{"$contentActions":[{"action":{"$id":"afa4a0ac-8bb5-4103-8232-85b50d5c1658","type":"SendMessage","settings":{"id":"ace63bb9-6ecd-4ea5-a7c3-03d9e0058cdc","type":"application/vnd.lime.chatstate+json","content":{"state":"composing","interval":1000}},"$cardContent":{"document":{"id":"ace63bb9-6ecd-4ea5-a7c3-03d9e0058cdc","type":"application/vnd.lime.chatstate+json","content":{"state":"composing","interval":1000}},"editable":true,"deletable":true,"position":"left"}},"$invalid":false},{"action":{"$id":"829730c5-bafb-4ea2-852f-79e6863717e9","type":"SendMessage","settings":{"id":"c7ba4a46-6f5e-48bf-b415-30150c079451","type":"text/plain","content":"Não temos medo de sonhar grande, pois sabemos que temos talento e determinação para realizar coisas incríveis!","metadata":{}},"$cardContent":{"document":{"id":"c7ba4a46-6f5e-48bf-b415-30150c079451","type":"text/plain","content":"Não temos medo de sonhar grande, pois sabemos que temos talento e determinação para realizar coisas incríveis!"},"editable":true,"deletable":true,"position":"left"}},"$invalid":false},{"input":{"bypass":true,"$cardContent":{"document":{"id":"3c16bfa2-5c40-4975-a5ca-6368dfbd940e","type":"text/plain","textContent":"Entrada do usuário","content":"Entrada do usuário"},"editable":false,"deletable":true,"position":"right","editing":false},"$invalid":false},"$invalid":false}],"$conditionOutputs":[],"$enteringCustomActions":[],"$leavingCustomActions":[],"$inputSuggestions":[],"$defaultOutput":{"stateId":"03b0c9e3-a6ce-466f-9f66-e202c5a4010b","$invalid":false},"$tags":[],"id":"9501bb11-db9a-4a85-b969-74e75cb0d2f4","root":false,"$title":"Take.Higher","$position":{"top":"503px","left":"887px"},"$invalidContentActions":false,"$invalidOutputs":false,"$invalidCustomActions":false,"$invalid":false},"03b0c9e3-a6ce-466f-9f66-e202c5a4010b":{"$contentActions":[{"action":{"$id":"ec331fb1-c59c-4e5f-a9ad-b13f6c55a1ec","type":"SendMessage","settings":{"id":"ed418da9-0248-432b-9a4d-38a16f497ec4","type":"application/vnd.lime.chatstate+json","content":{"state":"composing","interval":1000}},"$cardContent":{"document":{"id":"ed418da9-0248-432b-9a4d-38a16f497ec4","type":"application/vnd.lime.chatstate+json","content":{"state":"composing","interval":1000}},"editable":true,"deletable":true,"position":"left"}},"$invalid":false},{"action":{"$id":"04b39cd7-0d1f-44b7-92d9-6dd636603c58","type":"SendMessage","settings":{"id":"0edc8378-5be9-421b-b8ad-26f63fa24193","type":"application/vnd.lime.select+json","content":{"text":"Se quiser saber mais sobre algum dos outros valores, é só falar.","scope":"immediate","options":[{"text":"💙 Be","previewText":"💙 Be","value":null,"index":0,"type":null},{"text":"🏳️ Team","previewText":"🏳️ Team","value":null,"index":1,"type":null},{"index":-1,"text":"⭐ Excellence","previewText":"⭐ Excellence","type":null,"value":null},{"index":-1,"text":"⚡ Charge","previewText":"⚡ Charge","type":null,"value":null},{"index":-1,"text":"🎯 Simple","previewText":"🎯 Simple","type":null,"value":null},{"index":-1,"text":"🚀 Higher","previewText":"🚀 Higher","type":null,"value":null},{"index":-1,"text":"💡 Desafio","previewText":"💡 Desafio","type":null,"value":null}]},"metadata":{}},"$cardContent":{"document":{"id":"0edc8378-5be9-421b-b8ad-26f63fa24193","type":"application/vnd.lime.select+json","content":{"text":"Se quiser saber mais sobre algum dos outros valores, é só falar.","scope":"immediate","options":[{"text":"💙 Be","previewText":"💙 Be","value":null,"index":0,"type":null},{"text":"🏳️ Team","previewText":"🏳️ Team","value":null,"index":1,"type":null},{"index":-1,"text":"⭐ Excellence","previewText":"⭐ Excellence","type":null,"value":null},{"index":-1,"text":"⚡ Charge","previewText":"⚡ Charge","type":null,"value":null},{"index":-1,"text":"🎯 Simple","previewText":"🎯 Simple","type":null,"value":null},{"index":-1,"text":"🚀 Higher","previewText":"🚀 Higher","type":null,"value":null},{"index":-1,"text":"💡 Desafio","previewText":"💡 Desafio","type":null,"value":null}]}},"editable":true,"deletable":true,"position":"left"}},"$invalid":false},{"input":{"bypass":false,"$cardContent":{"document":{"id":"5fef22fb-97d7-4ed9-83d6-b6703e6ab7c1","type":"text/plain","textContent":"Entrada do usuário","content":"Entrada do usuário"},"editable":false,"deletable":true,"position":"right","editing":false},"$invalid":false},"$invalid":false}],"$conditionOutputs":[{"stateId":"5fb727dd-d01a-4837-9e12-e2f651e8a394","$connId":"con_23","$id":"28079748-0782-4b44-be49-7792ba76f45f","conditions":[{"source":"input","comparison":"exists","values":[]}],"$invalid":false}],"$enteringCustomActions":[],"$leavingCustomActions":[{"$id":"7e1c660a-dd0e-4ecb-9765-e7f8eb61a705","type":"SetVariable","$title":"Definir variável","$invalid":false,"settings":{"variable":"conhecerOutro","value":"{{input.content}}"},"conditions":[]}],"$inputSuggestions":["💙 Be","🏳️ Team","⭐ Excellence","⚡ Charge","🎯 Simple","🚀 Higher","💡 Desafio"],"$defaultOutput":{"stateId":"fallback","$invalid":false},"$tags":[],"id":"03b0c9e3-a6ce-466f-9f66-e202c5a4010b","root":false,"$title":"Conhecer outro?","$position":{"top":"777.143px","left":"499.571px"},"$invalidContentActions":false,"$invalidOutputs":false,"$invalidCustomActions":false,"$invalid":false},"c7f96bb8-bae7-47fb-9962-ef0b84ad487e":{"$contentActions":[{"action":{"$id":"9055e929-3957-4441-b2c8-b08948e39577","type":"SendMessage","settings":{"id":"878f5a6f-0a4d-4e8f-8818-a09fcd737df7","type":"application/vnd.lime.chatstate+json","content":{"state":"composing","interval":1000}},"$cardContent":{"document":{"id":"878f5a6f-0a4d-4e8f-8818-a09fcd737df7","type":"application/vnd.lime.chatstate+json","content":{"state":"composing","interval":1000}},"editable":true,"deletable":true,"position":"left"}},"$invalid":false},{"action":{"$id":"fee8da4f-6752-400d-8a63-83553b3d0129","type":"SendMessage","settings":{"id":"8e91dd9f-ee6c-48c0-986d-0f64e0b0ef0e","type":"text/plain","content":"Conforme solicitado no e-mail\nenviado, o resultado do desafio\nestá disponível abaixo...","metadata":{}},"$cardContent":{"document":{"id":"8e91dd9f-ee6c-48c0-986d-0f64e0b0ef0e","type":"text/plain","content":"Conforme solicitado no e-mail\nenviado, o resultado do desafio\nestá disponível abaixo..."},"editable":true,"deletable":true,"position":"left"}},"$invalid":false},{"input":{"bypass":true,"$cardContent":{"document":{"id":"67978db0-7f5e-4b6a-a3c5-967898253aaa","type":"text/plain","textContent":"Entrada do usuário","content":"Entrada do usuário"},"editable":false,"deletable":true,"position":"right","editing":false},"$invalid":false},"$invalid":false}],"$conditionOutputs":[{"stateId":"3ea262b5-6fec-44c8-ba31-8b8f912836a0","$connId":"con_28","$id":"2f8a33d2-77f2-4fb7-8374-0f803157a242","conditions":[{"source":"input","comparison":"exists","values":[]}],"$invalid":false}],"$enteringCustomActions":[{"$id":"398bb106-749a-457b-8a40-9757f01e6ec1","type":"ProcessHttp","$title":"Requisição HTTP","$invalid":false,"settings":{"headers":{},"method":"GET","uri":"https://fathomless-headland-97676.herokuapp.com/GitHubRepo?orgName=takeNet&upperLimit=15","responseStatusVariable":"statusResposta","responseBodyVariable":"corpoResposta"},"conditions":[]},{"$id":"262cd495-e55a-453c-a72f-f4317516f24f","type":"ExecuteScript","$title":"Executar script","$invalid":false,"settings":{"function":"run","source":"/**\n            * All input variables needs to be passed as function param;\n            * Objects received as param needs to be parsed. Ex.: JSON.parse(inputVariable1);\n            * Objects returned needs to be stringfied. Ex.: JSON.stringify(inputVariable1);\n            **/\n            function run(corpoResposta) {\n\n                parsed = JSON.parse(corpoResposta);               \n\n                output = {\n                    \"nome1\":parsed[0].name,\n                    \"nome2\":parsed[1].name,\n                    \"nome3\":parsed[2].name,\n                    \"nome4\":parsed[3].name,\n                    \"nome5\":parsed[4].name,\n\n                    \"descricao1\":parsed[0].description,\n                    \"descricao2\":parsed[1].description,\n                    \"descricao3\":parsed[2].description,\n                    \"descricao4\":parsed[3].description,\n                    \"descricao5\":parsed[4].description\n                };\n\n\n                return output; //Return value will be saved as \"Return value variable\" field name\n            }","inputVariables":["corpoResposta"],"outputVariable":"final","LocalTimeZoneEnabled":false},"conditions":[]}],"$leavingCustomActions":[],"$inputSuggestions":[],"$defaultOutput":{"stateId":"fallback","$invalid":false},"$tags":[],"id":"c7f96bb8-bae7-47fb-9962-ef0b84ad487e","root":false,"$title":"Desafio","$position":{"top":"779.429px","left":"728.286px"},"$invalidContentActions":false,"$invalidOutputs":false,"$invalidCustomActions":false,"$invalid":false},"5fb727dd-d01a-4837-9e12-e2f651e8a394":{"$contentActions":[{"input":{"bypass":true,"$cardContent":{"document":{"id":"817f78a3-e7a4-4f7d-9abb-61d55cdb08df","type":"text/plain","textContent":"Entrada do usuário","content":"Entrada do usuário"},"editable":false,"deletable":true,"position":"right","editing":false},"$invalid":false},"$invalid":false}],"$conditionOutputs":[{"stateId":"9787c43b-eba7-4134-b201-9e610aafae51","$connId":"con_33","$id":"fbb1d1bc-9613-4996-ac67-822670d1dd8c","conditions":[{"source":"context","comparison":"equals","variable":"conhecerOutro","values":["💙 Be"]}],"$invalid":false},{"stateId":"be256784-da9a-41a4-8529-f23feb121f1a","$connId":"con_38","$id":"280a2823-35a8-464c-99a1-68b028697e46","conditions":[{"source":"context","comparison":"equals","values":["🏳️ Team"],"variable":"conhecerOutro"}],"$invalid":false},{"stateId":"e585e39b-f0da-4a8f-8e97-523d7f4d961b","$connId":"con_43","$id":"ec48dfa9-e6b1-4117-b631-f9a4e8ae71ab","conditions":[{"source":"context","comparison":"equals","values":["⭐ Excellence"],"variable":"conhecerOutro"}],"$invalid":false},{"stateId":"07fb5a96-5234-4b4a-8abc-823fe45b6bd7","$connId":"con_48","$id":"ce803fb2-ba8e-456a-a24f-018f7d189fb3","conditions":[{"source":"context","comparison":"equals","values":["⚡ Charge"],"variable":"conhecerOutro"}],"$invalid":false},{"stateId":"9501bb11-db9a-4a85-b969-74e75cb0d2f4","$connId":"con_53","$id":"33c434a8-dbd7-4f3a-8d5d-dff1ebba383b","conditions":[{"source":"context","comparison":"equals","values":["🚀 Higher"],"variable":"conhecerOutro"}],"$invalid":false},{"stateId":"ec948a00-6f35-4597-b25d-3e610c4c8062","$connId":"con_58","$id":"7f57ad2f-606d-4186-9f1e-933ddd792414","conditions":[{"source":"context","comparison":"equals","values":["🎯 Simple"],"variable":"conhecerOutro"}],"$invalid":false},{"stateId":"c7f96bb8-bae7-47fb-9962-ef0b84ad487e","$connId":"con_63","$id":"8b07c25a-ff64-4c4f-af10-c7898b2da3d2","conditions":[{"source":"context","comparison":"equals","values":["💡 Desafio"],"variable":"conhecerOutro"}],"$invalid":false},{"stateId":"9787c43b-eba7-4134-b201-9e610aafae51","$connId":"con_68","$id":"472c83c0-7ed9-41e7-9008-681979bb5bd8","conditions":[{"source":"context","comparison":"equals","values":["💙 Saber mais"],"variable":"nomeValor"}],"$invalid":false},{"stateId":"be256784-da9a-41a4-8529-f23feb121f1a","$connId":"con_73","$id":"222a2a82-0bbf-4010-a42e-7a25f6fecab8","conditions":[{"source":"context","comparison":"equals","values":["🏳️ Saber mais"],"variable":"nomeValor"}],"$invalid":false},{"stateId":"e585e39b-f0da-4a8f-8e97-523d7f4d961b","$connId":"con_78","$id":"25dfd419-5609-4ad9-80d9-109324baa6f6","conditions":[{"source":"context","comparison":"equals","values":["⭐ Saber mais"],"variable":"nomeValor"}],"$invalid":false},{"stateId":"07fb5a96-5234-4b4a-8abc-823fe45b6bd7","$connId":"con_83","$id":"3d984eb9-acc0-405c-97cb-22bbfe52f705","conditions":[{"source":"context","comparison":"equals","values":["⚡ Saber mais"],"variable":"nomeValor"}],"$invalid":false},{"stateId":"ec948a00-6f35-4597-b25d-3e610c4c8062","$connId":"con_88","$id":"79f4bc93-aeca-4a89-a2fb-4f32c4e6a06e","conditions":[{"source":"context","comparison":"equals","values":["🎯 Saber mais"],"variable":"nomeValor"}],"$invalid":false},{"stateId":"9501bb11-db9a-4a85-b969-74e75cb0d2f4","$connId":"con_93","$id":"25d5b1e0-f37c-48c0-b2a4-0916e30f1179","conditions":[{"source":"context","comparison":"equals","values":["🚀 Saber mais"],"variable":"nomeValor"}],"$invalid":false},{"stateId":"c7f96bb8-bae7-47fb-9962-ef0b84ad487e","$connId":"con_98","$id":"0bcb1fd8-709c-46c5-b95a-f0d8b8d67d1a","conditions":[{"source":"context","comparison":"equals","values":["Fazer desafio"],"variable":"nomeValor"}],"$invalid":false}],"$enteringCustomActions":[],"$leavingCustomActions":[],"$inputSuggestions":[],"$defaultOutput":{"stateId":"fallback","$invalid":false},"$tags":[],"id":"5fb727dd-d01a-4837-9e12-e2f651e8a394","root":false,"$title":"Router","$position":{"top":"503px","left":"619px"},"$invalidContentActions":false,"$invalidOutputs":false,"$invalidCustomActions":false,"$invalid":false},"3ea262b5-6fec-44c8-ba31-8b8f912836a0":{"$contentActions":[{"action":{"$id":"dba075b7-7900-41df-9343-e8e723a62dd3","type":"SendMessage","settings":{"id":"ed0dc0f4-16c4-4059-ac0e-5bc9a5f0ccd1","type":"application/vnd.lime.chatstate+json","content":{"state":"composing","interval":1000}},"$cardContent":{"document":{"id":"ed0dc0f4-16c4-4059-ac0e-5bc9a5f0ccd1","type":"application/vnd.lime.chatstate+json","content":{"state":"composing","interval":1000}},"editable":true,"deletable":true,"position":"left"}},"$invalid":false},{"action":{"$id":"c5b06352-cf1b-4a92-bb1d-b64fdd4a06cd","type":"SendMessage","settings":{"id":"3434293f-2690-41c5-9bf7-e9ab40c0d759","type":"application/vnd.lime.collection+json","content":{"itemType":"application/vnd.lime.document-select+json","items":[{"header":{"type":"application/vnd.lime.media-link+json","value":{"title":"{{final@nome1}}","text":"{{final@descricao1}}","type":"image/png","uri":"https://i.imgur.com/9tTZx4l.png","aspectRatio":"2:1"}},"options":[],"id":0,"editing":false},{"header":{"type":"application/vnd.lime.media-link+json","value":{"title":"{{final@nome2}}","text":"{{final@descricao2}}","type":"image/png","uri":"https://i.imgur.com/9tTZx4l.png","aspectRatio":"2:1"}},"options":[],"editing":false,"id":1},{"header":{"type":"application/vnd.lime.media-link+json","value":{"title":"{{final@nome3}}","text":"{{final@descricao3}}","type":"image/png","uri":"https://i.imgur.com/9tTZx4l.png","aspectRatio":"2:1"}},"options":[],"editing":false,"id":2},{"header":{"type":"application/vnd.lime.media-link+json","value":{"title":"{{final@nome4}}","text":"{{final@descricao4}}","type":"image/png","uri":"https://i.imgur.com/9tTZx4l.png","aspectRatio":"2:1"}},"options":[],"editing":false,"id":3},{"header":{"type":"application/vnd.lime.media-link+json","value":{"title":"{{final@nome5}}","text":"{{final@descricao5}}","type":"image/png","uri":"https://i.imgur.com/9tTZx4l.png","aspectRatio":"2:1"}},"options":[],"editing":false,"id":4}]},"metadata":{}},"$cardContent":{"document":{"id":"3434293f-2690-41c5-9bf7-e9ab40c0d759","type":"application/vnd.lime.collection+json","content":{"itemType":"application/vnd.lime.document-select+json","items":[{"header":{"type":"application/vnd.lime.media-link+json","value":{"title":"{{final@nome1}}","text":"{{final@descricao1}}","type":"image/png","uri":"https://i.imgur.com/9tTZx4l.png","aspectRatio":"2:1"}},"options":[],"id":0,"editing":false},{"header":{"type":"application/vnd.lime.media-link+json","value":{"title":"{{final@nome2}}","text":"{{final@descricao2}}","type":"image/png","uri":"https://i.imgur.com/9tTZx4l.png","aspectRatio":"2:1"}},"options":[],"editing":false,"id":1},{"header":{"type":"application/vnd.lime.media-link+json","value":{"title":"{{final@nome3}}","text":"{{final@descricao3}}","type":"image/png","uri":"https://i.imgur.com/9tTZx4l.png","aspectRatio":"2:1"}},"options":[],"editing":false,"id":2},{"header":{"type":"application/vnd.lime.media-link+json","value":{"title":"{{final@nome4}}","text":"{{final@descricao4}}","type":"image/png","uri":"https://i.imgur.com/9tTZx4l.png","aspectRatio":"2:1"}},"options":[],"editing":false,"id":3},{"header":{"type":"application/vnd.lime.media-link+json","value":{"title":"{{final@nome5}}","text":"{{final@descricao5}}","type":"image/png","uri":"https://i.imgur.com/9tTZx4l.png","aspectRatio":"2:1"}},"options":[],"editing":false,"id":4}]}},"editable":true,"deletable":true,"position":"left"}},"$invalid":false},{"action":{"$id":"29419b85-6d90-4b07-b873-e1c32e738295","type":"SendMessage","settings":{"id":"2c09c89d-c7b8-46e3-9964-ce1c7f7e6390","type":"application/vnd.lime.chatstate+json","content":{"state":"composing","interval":1000}},"$cardContent":{"document":{"id":"2c09c89d-c7b8-46e3-9964-ce1c7f7e6390","type":"application/vnd.lime.chatstate+json","content":{"state":"composing","interval":1000}},"editable":true,"deletable":true,"position":"left"}},"$invalid":false},{"action":{"$id":"39836b0c-e77d-4ac8-9e99-41ee57e1c503","type":"SendMessage","settings":{"id":"d3991f60-1f01-464a-9142-403ca7a40b6c","type":"text/plain","content":"Esses são os 5 repositórios de C#\nmais antigos da Take no GitHub.","metadata":{}},"$cardContent":{"document":{"id":"d3991f60-1f01-464a-9142-403ca7a40b6c","type":"text/plain","content":"Esses são os 5 repositórios de C#\nmais antigos da Take no GitHub."},"editable":true,"deletable":true,"position":"left"}},"$invalid":false},{"input":{"bypass":false,"$cardContent":{"document":{"id":"ef4c3e3b-48d2-4b08-b222-3eb071d79e76","type":"text/plain","textContent":"Entrada do usuário","content":"Entrada do usuário"},"editable":false,"deletable":true,"position":"right","editing":false},"$invalid":false},"$invalid":false}],"$conditionOutputs":[],"$enteringCustomActions":[],"$leavingCustomActions":[],"$inputSuggestions":[],"$defaultOutput":{"stateId":"fallback","$invalid":false},"$tags":[],"id":"3ea262b5-6fec-44c8-ba31-8b8f912836a0","root":false,"$title":"Carousel Desafio","$position":{"top":"920px","left":"883px"},"$invalidContentActions":false,"$invalidOutputs":false,"$invalidCustomActions":false,"$invalid":false}}